Metadata-Version: 1.0
Name: tello-lbs
Version: 1.1
Summary: Tello Edu Extention KIT controller
Home-page: UNKNOWN
Author: UNKNOWN
Author-email: dimitriz@mail.ru
License: UNKNOWN
Platform: UNKNOWN
